jam/__init__.py
jam/config.py
jam/constant.py
jam/entry.py
jam/error.py
jam/log.py
jam/merge.py
jam/reference.py
jam/util.py
jam_tool-0.4.0.dist-info/LICENSE
jam_tool-0.4.0.dist-info/METADATA
jam_tool-0.4.0.dist-info/WHEEL
jam_tool-0.4.0.dist-info/entry_points.txt
jam_tool-0.4.0.dist-info/top_level.txt
jam_tool-0.4.0.dist-info/RECORD
